LICENSE
MANIFEST.in
README.md
setup.cfg
setup.py
tap_quickbase/__init__.py
tap_quickbase/qbconn.py
tap_quickbase.egg-info/PKG-INFO
tap_quickbase.egg-info/SOURCES.txt
tap_quickbase.egg-info/dependency_links.txt
tap_quickbase.egg-info/entry_points.txt
tap_quickbase.egg-info/requires.txt
tap_quickbase.egg-info/top_level.txt