Metadata-Version: 1.1
Name: tap-quickbase
Version: 0.3.4
Summary: Singer.io tap for extracting data from QuickBase
Home-page: https://singer.io
Author: Stitch
Author-email: UNKNOWN
License: UNKNOWN
Platform: UNKNOWN
Classifier: Programming Language :: Python :: 3 :: Only
